pywaterinfo/__init__.py
pywaterinfo/utils.py
pywaterinfo/waterinfo.py
pywaterinfo-0.8.1.dist-info/AUTHORS.rst
pywaterinfo-0.8.1.dist-info/LICENSE
pywaterinfo-0.8.1.dist-info/METADATA
pywaterinfo-0.8.1.dist-info/WHEEL
pywaterinfo-0.8.1.dist-info/top_level.txt
pywaterinfo-0.8.1.dist-info/RECORD
