Metadata-Version: 2.1
Name: pywaterinfo
Version: 0.8.1
Summary: Python package to download time series data from waterinfo.be
Home-page: https://github.com/fluves/pywaterinfo
Author: Stijn Van Hoey
Author-email: stijn@fluves.com
License: mit
Project-URL: Documentation, https://github.com/fluves/pywaterinfo
Platform: any
Classifier: Development Status :: 4 - Beta
Classifier: Programming Language :: Python
Classifier: Programming Language :: Python :: 3.8
Classifier: Programming Language :: Python :: 3.9
Classifier: Programming Language :: Python :: 3.10
Classifier: Programming Language :: Python :: 3.11
Classifier: Programming Language :: Python :: 3.12
Classifier: Intended Audience :: Science/Research
Classifier: Intended Audience :: Developers
Classifier: License :: OSI Approved :: MIT License
Requires-Python: >=3.7
License-File: LICENSE
License-File: AUTHORS.rst
Requires-Dist: pandas
Requires-Dist: requests
Requires-Dist: importlib-metadata; python_version < "3.8"
Provides-Extra: cache
Requires-Dist: requests-cache>=0.8; extra == "cache"
Provides-Extra: develop
Requires-Dist: tox; extra == "develop"
Requires-Dist: flake8; extra == "develop"
Requires-Dist: pytest; extra == "develop"
Requires-Dist: pytest-cov; extra == "develop"
Requires-Dist: sphinx; extra == "develop"
Requires-Dist: sphinx-rtd-theme; extra == "develop"
Requires-Dist: pre-commit>=2.9.2; extra == "develop"
Requires-Dist: black; extra == "develop"
Requires-Dist: nbstripout; extra == "develop"
Requires-Dist: setuptools-scm; extra == "develop"
